MANIFEST.in
requirements.txt
setup.py
test_requirements.txt
version.txt
cloudshell/__init__.py
cloudshell/cm/__init__.py
cloudshell/cm/customscript/__init__.py
cloudshell/cm/customscript/customscript_shell.py
cloudshell/cm/customscript/domain/__init__.py
cloudshell/cm/customscript/domain/cancellation_sampler.py
cloudshell/cm/customscript/domain/linux_script_executor.py
cloudshell/cm/customscript/domain/reservation_output_writer.py
cloudshell/cm/customscript/domain/script_configuration.py
cloudshell/cm/customscript/domain/script_downloader.py
cloudshell/cm/customscript/domain/script_executor.py
cloudshell/cm/customscript/domain/script_executor_selector.py
cloudshell/cm/customscript/domain/script_file.py
cloudshell/cm/customscript/domain/windows_script_executor.py
cloudshell_cm_customscript.egg-info/PKG-INFO
cloudshell_cm_customscript.egg-info/SOURCES.txt
cloudshell_cm_customscript.egg-info/dependency_links.txt
cloudshell_cm_customscript.egg-info/requires.txt
cloudshell_cm_customscript.egg-info/top_level.txt
tests/__init__.py
tests/helpers.py
tests/test_customscript_shell.py
tests/test_linux_script_executor.py
tests/test_reservation_output_writer.py
tests/test_script_configuration.py
tests/test_script_downloader.py
tests/test_script_executor_selector.py
tests/test_windows_script_executor.py